osbot_fast_api/__init__.py
osbot_fast_api/api/Fast_API.py
osbot_fast_api/api/Fast_API__Offline_Docs.py
osbot_fast_api/api/__init__.py
osbot_fast_api/api/decorators/Fast_API__Thread__Trace_Request.py
osbot_fast_api/api/decorators/__init__.py
osbot_fast_api/api/decorators/route_path.py
osbot_fast_api/api/middlewares/Middleware__Check_API_Key.py
osbot_fast_api/api/middlewares/Middleware__Detect_Disconnect.py
osbot_fast_api/api/middlewares/Middleware__Request_ID.py
osbot_fast_api/api/middlewares/__init__.py
osbot_fast_api/api/routes/Fast_API__Route__Helper.py
osbot_fast_api/api/routes/Fast_API__Route__Parser.py
osbot_fast_api/api/routes/Fast_API__Routes.py
osbot_fast_api/api/routes/Routes__Config.py
osbot_fast_api/api/routes/Routes__Set_Cookie.py
osbot_fast_api/api/routes/__init__.py
osbot_fast_api/api/routes/type_safe/Type_Safe__Route__Analyzer.py
osbot_fast_api/api/routes/type_safe/Type_Safe__Route__Converter.py
osbot_fast_api/api/routes/type_safe/Type_Safe__Route__Registration.py
osbot_fast_api/api/routes/type_safe/Type_Safe__Route__Wrapper.py
osbot_fast_api/api/routes/type_safe/__init__.py
osbot_fast_api/api/schemas/Schema__Fast_API__Config.py
osbot_fast_api/api/schemas/Schema__Fast_API__Tag__Classes_And_Routes.py
osbot_fast_api/api/schemas/Schema__Fast_API__Tags__Classes_And_Routes.py
osbot_fast_api/api/schemas/__init__.py
osbot_fast_api/api/schemas/consts/__init__.py
osbot_fast_api/api/schemas/consts/consts__Fast_API.py
osbot_fast_api/api/schemas/enums/Enum__Fast_API__Route__Type.py
osbot_fast_api/api/schemas/enums/__init__.py
osbot_fast_api/api/schemas/routes/Schema__Fast_API__Route.py
osbot_fast_api/api/schemas/routes/Schema__Fast_API__Routes__Collection.py
osbot_fast_api/api/schemas/routes/Schema__Route__Parameter.py
osbot_fast_api/api/schemas/routes/Schema__Route__Signature.py
osbot_fast_api/api/schemas/routes/__init__.py
osbot_fast_api/api/schemas/safe_str/Safe_Str__Fast_API__Name.py
osbot_fast_api/api/schemas/safe_str/Safe_Str__Fast_API__Route__Prefix.py
osbot_fast_api-0.38.0.dist-info/LICENSE
osbot_fast_api-0.38.0.dist-info/METADATA
osbot_fast_api-0.38.0.dist-info/WHEEL
osbot_fast_api-0.38.0.dist-info/RECORD
