Metadata-Version: 2.1
Name: osbot_fast_api
Version: 0.38.0
Summary: OWASP Security Bot - Fast API
Home-page: https://github.com/owasp-sbot/OSBot-Fast-API
License: MIT
Author: Dinis Cruz
Author-email: dinis.cruz@owasp.org
Requires-Python: >=3.11,<4.0
Classifier: License :: OSI Approved :: MIT License
Classifier: Programming Language :: Python :: 3
Classifier: Programming Language :: Python :: 3.11
Classifier: Programming Language :: Python :: 3.12
Requires-Dist: fastapi
Requires-Dist: osbot-utils
Requires-Dist: requests
Requires-Dist: uvicorn
Project-URL: Repository, https://github.com/owasp-sbot/OSBot-Fast-API
